setup.py
thingosdci.sh
thingosdci/__init__.py
thingosdci/building.py
thingosdci/dockerctl.py
thingosdci/loopdevmanager.py
thingosdci/main.py
thingosdci/persist.py
thingosdci/s3client.py
thingosdci/settings.py
thingosdci/utils.py
thingosdci.egg-info/PKG-INFO
thingosdci.egg-info/SOURCES.txt
thingosdci.egg-info/dependency_links.txt
thingosdci.egg-info/entry_points.txt
thingosdci.egg-info/requires.txt
thingosdci.egg-info/top_level.txt
thingosdci/../thingosdci.sh
thingosdci/reposervices/__init__.py
thingosdci/reposervices/bitbucket.py
thingosdci/reposervices/github.py
thingosdci/reposervices/gitlab.py
thingosdci/reposervices/trigger.py