Metadata-Version: 1.0
Name: thingosdci
Version: 0.6.2
Summary: thingOS Docker CI
Home-page: https://github.com/ccrisan/thingosdci
Author: Calin Crisan
Author-email: ccrisan@gmail.com
License: GPLv3
Platform: UNKNOWN
